zuper_html_plus.cpython-310-x86_64-linux-gnu.so
zuper_html_plus.pyi
zuper_html_plus/html_from_object.css
zuper_html_plus_z7-7.3.2202211108.dist-info/WHEEL
zuper_html_plus_z7-7.3.2202211108.dist-info/top_level.txt
zuper_html_plus_z7-7.3.2202211108.dist-info/RECORD
zuper_html_plus_z7-7.3.2202211108.dist-info/METADATA
zuper_html_plus_z7-7.3.2202211108.dist-info/zip-safe
